koala/Cell.py
koala/CellBase.py
koala/ExcelCompiler.py
koala/ExcelError.py
koala/Range.py
koala/Spreadsheet.py
koala/__init__.py
koala/excellib.py
koala/functions.json
koala/reader.py
koala/serializer.py
koala/tokenizer.py
koala/utils.py
koala/ast/__init__.py
koala/ast/astnodes.py
tests/__init__.py
tests/ast/__init__.py
tests/ast/test_basic_evaluation.py
tests/ast/test_compile.py
tests/ast/test_pruning.py
tests/ast/test_range.py
tests/excel/__init__.py
tests/excel/test_excel.py
tests/excel/test_functions.py
tests/excel/test_spreadsheet.py
tests/excel/test_utils.py
koala2-0.0.35.dist-info/LICENSE.txt
koala2-0.0.35.dist-info/METADATA
koala2-0.0.35.dist-info/WHEEL
koala2-0.0.35.dist-info/top_level.txt
koala2-0.0.35.dist-info/RECORD
