Metadata-Version: 2.1
Name: koala2
Version: 0.0.35
Summary: A python module to extract all the content of an Excel document and enable calculation without Excel
Home-page: https://github.com/anthill/koala
Author: Ants, open innovation lab
Author-email: contact@weareants.fr
License: GNU GPL3
Platform: UNKNOWN
Requires-Dist: networkx (>=2.1)
Requires-Dist: openpyxl (>=2.5.3)
Requires-Dist: numpy (>=1.14.2)
Requires-Dist: Cython (>=0.28.2)
Requires-Dist: lxml (>=4.1.1)
Requires-Dist: six (>=1.11.0)
